ddcomp/__init__.py
ddcomp-0.5.dist-info/DESCRIPTION.rst
ddcomp-0.5.dist-info/METADATA
ddcomp-0.5.dist-info/RECORD
ddcomp-0.5.dist-info/WHEEL
ddcomp-0.5.dist-info/metadata.json
ddcomp-0.5.dist-info/top_level.txt
